[{"model": "chara.charaachievementcategory", "pk": 1, "fields": {"created_at": "2022-02-07T16:45:45.137Z", "updated_at": "2022-02-07T16:45:45.137Z", "name": "轉職次數"}}, {"model": "chara.charaachievementcategory", "pk": 2, "fields": {"created_at": "2022-02-07T16:45:45.137Z", "updated_at": "2022-02-07T16:45:45.138Z", "name": "轉職為N階職業"}}, {"model": "chara.charaachievementcategory", "pk": 3, "fields": {"created_at": "2022-02-07T16:45:45.138Z", "updated_at": "2022-02-07T16:45:45.138Z", "name": "最高轉職繼承率"}}, {"model": "chara.charaachievementcategory", "pk": 4, "fields": {"created_at": "2022-02-07T16:45:45.138Z", "updated_at": "2022-02-07T16:45:45.138Z", "name": "加入國家次數"}}, {"model": "chara.charaachievementcategory", "pk": 5, "fields": {"created_at": "2022-02-07T16:45:45.138Z", "updated_at": "2022-02-07T16:45:45.138Z", "name": "發起神獸戰次數"}}, {"model": "chara.charaachievementcategory", "pk": 6, "fields": {"created_at": "2022-02-07T16:45:45.138Z", "updated_at": "2022-02-07T16:45:45.138Z", "name": "地圖移動次數"}}, {"model": "chara.charaachievementcategory", "pk": 7, "fields": {"created_at": "2022-02-07T16:45:45.138Z", "updated_at": "2022-02-07T16:45:45.138Z", "name": "開寶箱次數"}}, {"model": "chara.charaachievementcategory", "pk": 8, "fields": {"created_at": "2022-02-07T16:45:45.138Z", "updated_at": "2022-02-07T16:45:45.138Z", "name": "注入成功次數"}}, {"model": "chara.charaachievementcategory", "pk": 9, "fields": {"created_at": "2022-02-07T16:45:45.138Z", "updated_at": "2022-02-07T16:45:45.138Z", "name": "注入失敗次數"}}, {"model": "chara.charaachievementcategory", "pk": 10, "fields": {"created_at": "2022-02-07T16:45:45.139Z", "updated_at": "2022-02-07T16:45:45.139Z", "name": "農場收穫次數"}}, {"model": "chara.charaachievementcategory", "pk": 11, "fields": {"created_at": "2022-02-07T16:45:45.139Z", "updated_at": "2022-02-07T16:45:45.139Z", "name": "國家資金捐獻數量"}}, {"model": "chara.charaachievementcategory", "pk": 12, "fields": {"created_at": "2022-02-09T13:20:22.866Z", "updated_at": "2022-02-09T13:20:22.866Z", "name": "注入連續失敗"}}, {"model": "chara.charaachievementcategory", "pk": 13, "fields": {"created_at": "2022-02-09T13:55:36.005Z", "updated_at": "2022-02-09T13:55:36.005Z", "name": "轉換裝備次數"}}, {"model": "chara.charaachievementcategory", "pk": 14, "fields": {"created_at": "2022-02-09T13:56:24.594Z", "updated_at": "2022-02-09T13:56:24.594Z", "name": "裝備更名次數"}}, {"model": "chara.charaachievementcategory", "pk": 15, "fields": {"created_at": "2022-02-09T13:57:35.960Z", "updated_at": "2022-02-09T13:57:35.960Z", "name": "購入彩票次數"}}, {"model": "chara.charaachievementcategory", "pk": 16, "fields": {"created_at": "2022-02-09T13:58:51.610Z", "updated_at": "2022-02-09T13:58:51.610Z", "name": "地圖製作累計失敗張數"}}, {"model": "chara.charaachievementcategory", "pk": 17, "fields": {"created_at": "2022-02-09T13:59:49.834Z", "updated_at": "2022-02-09T13:59:49.835Z", "name": "競技場獲勝次數"}}, {"model": "chara.charaachievementcategory", "pk": 18, "fields": {"created_at": "2022-02-09T14:00:37.085Z", "updated_at": "2022-02-09T14:00:37.085Z", "name": "彩券中獎次數"}}, {"model": "chara.charaachievementcategory", "pk": 19, "fields": {"created_at": "2022-02-09T14:01:39.860Z", "updated_at": "2022-02-09T14:01:39.860Z", "name": "達成任務次數"}}, {"model": "chara.charaachievementcategory", "pk": 20, "fields": {"created_at": "2022-02-12T14:00:18.756Z", "updated_at": "2022-02-12T14:00:18.756Z", "name": "改名次數"}}, {"model": "chara.charaachievementcategory", "pk": 22, "fields": {"created_at": "2022-02-12T14:03:27.909Z", "updated_at": "2022-02-12T14:03:27.909Z", "name": "換頭貼次數"}}, {"model": "chara.charaachievementcategory", "pk": 23, "fields": {"created_at": "2022-02-12T14:04:35.248Z", "updated_at": "2022-02-12T14:04:35.248Z", "name": "強化裝備次數"}}, {"model": "chara.charaachievementcategory", "pk": 24, "fields": {"created_at": "2022-02-12T14:05:48.954Z", "updated_at": "2022-02-12T14:05:48.954Z", "name": "裝備屬性轉換次數"}}, {"model": "chara.charaachievementcategory", "pk": 25, "fields": {"created_at": "2022-02-12T14:11:48.485Z", "updated_at": "2022-02-12T14:11:48.485Z", "name": "召喚NPC時數"}}, {"model": "chara.charaachievementcategory", "pk": 26, "fields": {"created_at": "2022-02-12T14:12:45.171Z", "updated_at": "2022-02-12T14:12:45.171Z", "name": "使用buff道具次數"}}]